{"police":{"monthlyGenerated":0,"applications":false,"stars":[],"name":"police","webhooks":[],"label":"Police","employees":[],"currentMonth":"04"},"burgershot":{"monthlyGenerated":373,"applications":false,"stars":[],"name":"burgershot","webhooks":[],"label":"Burgershot","employees":{"3f692cc":{"generated":112,"image":"","activities":2,"phone":"","hours":0,"name":"JJ Dev","lastSeen":"","grade":{"level":4,"name":"Owner"},"permissions":[],"identifier":"3f692cc"}},"currentMonth":"04"},"avscripts":{"monthlyGenerated":0,"applications":false,"stars":[],"name":"avscripts","webhooks":[],"label":"AV Scripts","employees":[],"currentMonth":"04"}}